redactify_ai/__init__.py
redactify_ai/config.py
redactify_ai/custom_recognizers.py
redactify_ai/download_model.py
redactify_ai/processor.py
redactify_ai/utils.py
redactify_ai-0.0.1.dist-info/licenses/LICENSE
redactify_ai-0.0.1.dist-info/METADATA
redactify_ai-0.0.1.dist-info/WHEEL
redactify_ai-0.0.1.dist-info/top_level.txt
redactify_ai-0.0.1.dist-info/RECORD
