Metadata-Version: 2.4
Name: redactify-ai
Version: 0.0.1
Summary: A Python package for leveraging Presidio for anonymizing sensitive PII data using Spark.
Home-page: https://gitlab.com/rokorolev/redactify-ai
Author: Roman Korolev
Author-email: spark_development@yahoo.com
License: MIT
Classifier: Programming Language :: Python :: 3
Classifier: License :: OSI Approved :: MIT License
Classifier: Operating System :: OS Independent
Classifier: Topic :: Software Development :: Libraries :: Python Modules
Requires-Python: >=3.11
License-File: LICENSE
Requires-Dist: pyyaml==6.0.1
Requires-Dist: pandas==1.5.3
Requires-Dist: spacy==3.7.5
Requires-Dist: presidio_analyzer~=2.2.358
Requires-Dist: presidio_anonymizer~=2.2.358
Requires-Dist: requests==2.32.2
Requires-Dist: urllib3==1.26.16
Requires-Dist: pyspark==3.5.2
Dynamic: author
Dynamic: author-email
Dynamic: classifier
Dynamic: description
Dynamic: description-content-type
Dynamic: home-page
Dynamic: license
Dynamic: license-file
Dynamic: requires-dist
Dynamic: requires-python
Dynamic: summary
